[{"round": 1, "data": {"scores": {"original": 0, "current": 0, "initGPTscore": null}, "Reviews": {"original": "", "current": "", "added": "", "removed": ""}}}, {"round": 2, "data": {"scores": {"original": 5, "current": 5, "initGPTscore": 5}, "Reviews": {"original": "The artwork masterfully employs contrasting colors to create a striking and effective visual impact. The use of vibrant colors such as red, blue, yellow, and purple in the clothing of the characters, along with the rainbow and the colorful background, creates a lively and engaging scene. The contrast between the bright colors and the black hair of the characters further enhances the visual appeal. The cupcake's warm colors also stand out against the cooler background, drawing attention to it. Overall, the effective use of contrasting colors significantly enhances the artistic expression of the piece.", "current": "The artwork masterfully employs contrasting colors to create a striking and effective visual impact. The use of vibrant colors such as red, blue, yellow, and purple in the clothing of the characters, along with the rainbow and the colorful background, creates a lively and engaging scene. The contrast between the bright colors and the black hair of the characters further enhances the visual appeal. The cupcake's warm colors also stand out against the cooler background, drawing attention to it. Overall, the effective use of contrasting colors significantly enhances the artistic expression of the piece.", "added": "", "removed": ""}}}]