[{"round": 1, "data": {"suggestions": {"original": "", "current": "", "added": "", "removed": ""}}}, {"round": 2, "data": {"suggestions": {"original": "To further enhance the color richness of the artwork, consider incorporating more gradient transitions and shading within the existing colors. This can add depth and dimension to the elements, making them appear more dynamic and three-dimensional. Additionally, introducing subtle variations in hue and saturation within each color can create a more nuanced and sophisticated palette. Experimenting with complementary and contrasting colors can also bring out the vibrancy and make the composition even more engaging.", "current": "To further enhance the color richness of the artwork, consider incorporating more gradient transitions and shading within the existing colors. This can add depth and dimension to the elements, making them appear more dynamic and three-dimensional. Additionally, introducing subtle variations in hue and saturation within each color can create a more nuanced and sophisticated palette. Experimenting with complementary and contrasting colors can also bring out the vibrancy and make the composition even more engaging.", "added": "", "removed": ""}}}]